cabu/__init__.py
cabu/auth.py
cabu/core.py
cabu/default_settings.py
cabu/drivers.py
cabu/exceptions.py
cabu-0.0.2.dist-info/DESCRIPTION.rst
cabu-0.0.2.dist-info/METADATA
cabu-0.0.2.dist-info/RECORD
cabu-0.0.2.dist-info/WHEEL
cabu-0.0.2.dist-info/metadata.json
cabu-0.0.2.dist-info/pbr.json
cabu-0.0.2.dist-info/top_level.txt
cabu-0.0.2.dist-info/zip-safe
