Metadata-Version: 2.0
Name: cabu
Version: 0.0.2
Summary: cabu is a simple REST microservice to scrap content from anywhere.
Home-page: http://github.com/thylong/cabu
Author: Theotime Leveque
Author-email: theotime.leveque@gmail.com
License: BSD
Platform: any
Classifier: Environment :: Web Environment
Classifier: Intended Audience :: Developers
Classifier: License :: OSI Approved :: BSD License
Classifier: Operating System :: OS Independent
Classifier: Programming Language :: Python
Classifier: Programming Language :: Python :: 3
Classifier: Programming Language :: Python :: 3.5
Classifier: Topic :: Internet :: WWW/HTTP :: Dynamic Content
Requires-Dist: beautifulsoup4 (>=2.9.1)
Requires-Dist: flask (>=0.10.1,<0.11.0)
Requires-Dist: ftpretty (>=0.2.3,<0.3.0)
Requires-Dist: requests
Requires-Dist: requests-aws (<1.11.0)
Requires-Dist: selenium (>=2.50.0,<2.52.0)
Requires-Dist: six (>=0.1.8)
Requires-Dist: xvfbwrapper (>=0.2.7,<0.2.8)
